facefeaturelib/__init__.py
facefeaturelib/face_detector.py
facefeaturelib/inference_onnx.py
facefeaturelib/scrfd.py
facefeaturelib-0.1.0.dist-info/METADATA
facefeaturelib-0.1.0.dist-info/WHEEL
facefeaturelib-0.1.0.dist-info/top_level.txt
facefeaturelib-0.1.0.dist-info/RECORD
