Metadata-Version: 2.1
Name: facefeaturelib
Version: 0.1.0
Summary: image feature library
Home-page: UNKNOWN
Author: hoangvd3
Author-email: UNKNOWN
License: MIT
Platform: UNKNOWN
